privatefunc.py
privatefunc-1.6.23.dist-info/LICENSE
privatefunc-1.6.23.dist-info/METADATA
privatefunc-1.6.23.dist-info/WHEEL
privatefunc-1.6.23.dist-info/top_level.txt
privatefunc-1.6.23.dist-info/RECORD
