Metadata-Version: 2.1
Name: privatefunc
Version: 1.6.23
Summary: Create private functions in Python
Author-email: "Md. Faheem Hossain" <fmhossain2941@gmail.com>
Project-URL: Homepage, https://github.com/Faheem41/Private-Function-in-Python
Project-URL: Bug Tracker, https://github.com/Faheem41/Private-Function-in-Python/issues
Classifier: Programming Language :: Python :: 3
Classifier: License :: OSI Approved :: MIT License
Classifier: Operating System :: OS Independent
Requires-Python: >=3.7
License-File: LICENSE
